  {
    "subjects": [
      {
        "code": "tienganh",
        "name": "Tiếng Anh",
        "grade": 9,
        "chapters": [
          {
            "title": "Unit 1: Local Community (Cộng đồng địa phương)",
            "orderNo": 1,
            "lessons": [
              {
                "title": "Bài 1: Getting Started - A special day",
                "videoUrl": "https://flutter.github.io/assets-for-api-docs/assets/videos/bee.mp4",
                "contents": [
                  { "type": "text", "value": "Giới thiệu về trường học mới và những trải nghiệm đầu tiên." },
                  { "type": "image", "value": "https://images.unsplash.com/photo-1507525428034-b723cf961d3e" },
                  { "type": "text", "value": "Giới thiệu về trường học mới và những trải nghiệm đầu tiên." },
                  { "type": "image", "value": "https://images.unsplash.com/photo-1507525428034-b723cf961d3e" },
                  { "type": "text", "value": "Giới thiệu về trường học mới và những trải nghiệm đầu tiên." },
                  { "type": "image", "value": "https://images.unsplash.com/photo-1507525428034-b723cf961d3e" },
                  { "type": "text", "value": "Giới thiệu về trường học mới và những trải nghiệm đầu tiên." },
                  { "type": "image", "value": "https://images.unsplash.com/photo-1507525428034-b723cf961d3e" }
                ],
                "exercises": [
                  {
                    "question": "Write 5 sentences to introduce yourself in English.",
                    "solutions": [
                      { "type": "text", "value": "Hello, my name is Nam. I am twelve years old. I am a student in class 6A. My favorite subject is English. I like playing football with my friends." },
                      { "type": "text", "value": "When writing, remember to include name, age, class, favorite subject, and hobby." },
                      { "type": "image", "value": "https://images.unsplash.com/photo-1529070538774-1843cb3265df" },
                      { "type": "text", "value": "Use simple present tense (am, is, like, play)." },
                      { "type": "text", "value": "Each sentence should be short and clear." }
                    ]
                  },
                  {
                    "question": "Match the English words with their meanings in Vietnamese: (1) Teacher, (2) Student, (3) School, (4) Book.",
                    "solutions": [
                      { "type": "text", "value": "Teacher → Giáo viên" },
                      { "type": "text", "value": "Student → Học sinh" },
                      { "type": "text", "value": "School → Trường học" },
                      { "type": "text", "value": "Book → Quyển sách" },
                      { "type": "image", "value": "https://images.unsplash.com/photo-1503676260728-1c00da094a0b" }
                    ]
                  }
                ]
              },
              {
                "title": "Bài 2: A Closer Look 1 - Vocabulary & Pronunciation",
                "videoUrl": "https://flutter.github.io/assets-for-api-docs/assets/videos/bee.mp4",
                "contents": [
                  { "type": "text", "value": "Học từ vựng và cách phát âm về chủ đề trường học." },
                  { "type": "text", "value": "Giới thiệu về trường học mới và những trải nghiệm đầu tiên." },
                  { "type": "image", "value": "https://images.unsplash.com/photo-1507525428034-b723cf961d3e" },
                  { "type": "text", "value": "Giới thiệu về trường học mới và những trải nghiệm đầu tiên." },
                  { "type": "image", "value": "https://images.unsplash.com/photo-1507525428034-b723cf961d3e" },
                  { "type": "text", "value": "Giới thiệu về trường học mới và những trải nghiệm đầu tiên." },
                  { "type": "image", "value": "https://images.unsplash.com/photo-1507525428034-b723cf961d3e" }
                ],
                "exercises": [
                  {
                    "question": "Write 5 sentences to introduce yourself in English.",
                    "solutions": [
                      { "type": "text", "value": "Hello, my name is Nam. I am twelve years old. I am a student in class 6A. My favorite subject is English. I like playing football with my friends." },
                      { "type": "text", "value": "When writing, remember to include name, age, class, favorite subject, and hobby." },
                      { "type": "image", "value": "https://images.unsplash.com/photo-1529070538774-1843cb3265df" },
                      { "type": "text", "value": "Use simple present tense (am, is, like, play)." },
                      { "type": "text", "value": "Each sentence should be short and clear." }
                    ]
                  },
                  {
                    "question": "Match the English words with their meanings in Vietnamese: (1) Teacher, (2) Student, (3) School, (4) Book.",
                    "solutions": [
                      { "type": "text", "value": "Teacher → Giáo viên" },
                      { "type": "text", "value": "Student → Học sinh" },
                      { "type": "text", "value": "School → Trường học" },
                      { "type": "text", "value": "Book → Quyển sách" },
                      { "type": "image", "value": "https://images.unsplash.com/photo-1503676260728-1c00da094a0b" }
                    ]
                  }
                ]
              },
              {
                "title": "Bài 3: A Closer Look 2 - Grammar",
                "videoUrl": "https://flutter.github.io/assets-for-api-docs/assets/videos/bee.mp4",
                "contents": [
                  { "type": "text", "value": "Ôn tập thì hiện tại đơn và thì hiện tại tiếp diễn trong ngữ cảnh trường học." }
                ],
                "exercises": [
                  {
                    "question": "Write 5 sentences to introduce yourself in English.",
                    "solutions": [
                      { "type": "text", "value": "Hello, my name is Nam. I am twelve years old. I am a student in class 6A. My favorite subject is English. I like playing football with my friends." },
                      { "type": "text", "value": "When writing, remember to include name, age, class, favorite subject, and hobby." },
                      { "type": "image", "value": "https://images.unsplash.com/photo-1529070538774-1843cb3265df" },
                      { "type": "text", "value": "Use simple present tense (am, is, like, play)." },
                      { "type": "text", "value": "Each sentence should be short and clear." }
                    ]
                  },
                  {
                    "question": "Match the English words with their meanings in Vietnamese: (1) Teacher, (2) Student, (3) School, (4) Book.",
                    "solutions": [
                      { "type": "text", "value": "Teacher → Giáo viên" },
                      { "type": "text", "value": "Student → Học sinh" },
                      { "type": "text", "value": "School → Trường học" },
                      { "type": "text", "value": "Book → Quyển sách" },
                      { "type": "image", "value": "https://images.unsplash.com/photo-1503676260728-1c00da094a0b" }
                    ]
                  }
                ]
              },
              {
                "title": "Bài 4: Communication",
                "videoUrl": "https://flutter.github.io/assets-for-api-docs/assets/videos/bee.mp4",
                "contents": [
                  { "type": "text", "value": "Luyện tập kỹ năng giao tiếp về chủ đề trường học mới." }
                ],
                "exercises": [
                  {
                    "question": "Write 5 sentences to introduce yourself in English.",
                    "solutions": [
                      { "type": "text", "value": "Hello, my name is Nam. I am twelve years old. I am a student in class 6A. My favorite subject is English. I like playing football with my friends." },
                      { "type": "text", "value": "When writing, remember to include name, age, class, favorite subject, and hobby." },
                      { "type": "image", "value": "https://images.unsplash.com/photo-1529070538774-1843cb3265df" },
                      { "type": "text", "value": "Use simple present tense (am, is, like, play)." },
                      { "type": "text", "value": "Each sentence should be short and clear." }
                    ]
                  },
                  {
                    "question": "Match the English words with their meanings in Vietnamese: (1) Teacher, (2) Student, (3) School, (4) Book.",
                    "solutions": [
                      { "type": "text", "value": "Teacher → Giáo viên" },
                      { "type": "text", "value": "Student → Học sinh" },
                      { "type": "text", "value": "School → Trường học" },
                      { "type": "text", "value": "Book → Quyển sách" },
                      { "type": "image", "value": "https://images.unsplash.com/photo-1503676260728-1c00da094a0b" }
                    ]
                  }
                ]

              },
              {
                "title": "Bài 5: Skills 1 - Reading & Speaking",
                "videoUrl": "https://flutter.github.io/assets-for-api-docs/assets/videos/bee.mp4",
                "contents": [
                  { "type": "text", "value": "Rèn luyện kỹ năng đọc hiểu và thảo luận về trường học mới." }
                ],
                "exercises": [
                  {
                    "question": "Write 5 sentences to introduce yourself in English.",
                    "solutions": [
                      { "type": "text", "value": "Hello, my name is Nam. I am twelve years old. I am a student in class 6A. My favorite subject is English. I like playing football with my friends." },
                      { "type": "text", "value": "When writing, remember to include name, age, class, favorite subject, and hobby." },
                      { "type": "image", "value": "https://images.unsplash.com/photo-1529070538774-1843cb3265df" },
                      { "type": "text", "value": "Use simple present tense (am, is, like, play)." },
                      { "type": "text", "value": "Each sentence should be short and clear." }
                    ]
                  },
                  {
                    "question": "Match the English words with their meanings in Vietnamese: (1) Teacher, (2) Student, (3) School, (4) Book.",
                    "solutions": [
                      { "type": "text", "value": "Teacher → Giáo viên" },
                      { "type": "text", "value": "Student → Học sinh" },
                      { "type": "text", "value": "School → Trường học" },
                      { "type": "text", "value": "Book → Quyển sách" },
                      { "type": "image", "value": "https://images.unsplash.com/photo-1503676260728-1c00da094a0b" }
                    ]
                  }
                ]

              },
              {
                "title": "Bài 6: Skills 2 - Listening & Writing",
                "videoUrl": "https://flutter.github.io/assets-for-api-docs/assets/videos/bee.mp4",
                "contents": [
                  { "type": "text", "value": "Luyện kỹ năng nghe và viết về trải nghiệm ngày đầu đến trường." }
                ]
              },
              {
                "title": "Bài 7: Looking Back & Project",
                "videoUrl": "https://flutter.github.io/assets-for-api-docs/assets/videos/bee.mp4",
                "contents": [
                  { "type": "text", "value": "Ôn tập từ vựng, ngữ pháp và hoàn thành dự án nhóm." }
                ]
              }
            ]
          },
          {
            "title": "Unit 2: City Life (Cuộc sống thành phố)",
            "orderNo": 2,
            "lessons": [
              {
                "title": "Bài 1: Getting Started - My new house",
                "videoUrl": "https://flutter.github.io/assets-for-api-docs/assets/videos/bee.mp4",
                "contents": [
                  { "type": "text", "value": "Giới thiệu về ngôi nhà mới và các đồ dùng trong gia đình." }
                ]
              },
              {
                "title": "Bài 2: A Closer Look 1 - Vocabulary & Pronunciation",
                "videoUrl": "https://flutter.github.io/assets-for-api-docs/assets/videos/bee.mp4",
                "contents": [
                  { "type": "text", "value": "Học từ vựng và cách phát âm về các phòng và đồ nội thất trong nhà." }
                ]
              },
              {
                "title": "Bài 3: A Closer Look 2 - Grammar",
                "videoUrl": "https://flutter.github.io/assets-for-api-docs/assets/videos/bee.mp4",
                "contents": [
                  { "type": "text", "value": "Luyện cấu trúc There is/There are và giới từ chỉ vị trí." }
                ]
              },
              {
                "title": "Bài 4: Communication",
                "videoUrl": "https://flutter.github.io/assets-for-api-docs/assets/videos/bee.mp4",
                "contents": [
                  { "type": "text", "value": "Luyện hội thoại về việc miêu tả nhà cửa và các phòng trong nhà." }
                ]
              },
              {
                "title": "Bài 5: Skills 1 - Reading & Speaking",
                "videoUrl": "https://flutter.github.io/assets-for-api-docs/assets/videos/bee.mp4",
                "contents": [
                  { "type": "text", "value": "Rèn kỹ năng đọc hiểu và thuyết trình về ngôi nhà yêu thích của mình." }
                ]
              },
              {
                "title": "Bài 6: Skills 2 - Listening & Writing",
                "videoUrl": "https://flutter.github.io/assets-for-api-docs/assets/videos/bee.mp4",
                "contents": [
                  { "type": "text", "value": "Luyện nghe hội thoại và viết đoạn văn mô tả căn phòng yêu thích." }
                ]
              },
              {
                "title": "Bài 7: Looking Back & Project",
                "videoUrl": "https://flutter.github.io/assets-for-api-docs/assets/videos/bee.mp4",
                "contents": [
                  { "type": "text", "value": "Ôn tập từ vựng, ngữ pháp và làm dự án về thiết kế một căn phòng mơ ước." }
                ]
              }
            ]
          },
          {
            "title": "Unit 3: Teen Stress and Pressure (Áp lực và căng thẳng của thiếu niên)",
            "orderNo": 3,
            "lessons": [
              {
                "title": "Bài 1: Getting Started - My best friend",
                "videoUrl": "https://flutter.github.io/assets-for-api-docs/assets/videos/bee.mp4",
                "contents": [
                  { "type": "text", "value": "Giới thiệu và miêu tả người bạn thân nhất của bạn." }
                ]
              },
              {
                "title": "Bài 2: A Closer Look 1 - Vocabulary & Pronunciation",
                "videoUrl": "https://flutter.github.io/assets-for-api-docs/assets/videos/bee.mp4",
                "contents": [
                  { "type": "text", "value": "Học từ vựng và phát âm về tính cách, sở thích của bạn bè." }
                ]
              },
              {
                "title": "Bài 3: A Closer Look 2 - Grammar",
                "videoUrl": "https://flutter.github.io/assets-for-api-docs/assets/videos/bee.mp4",
                "contents": [
                  { "type": "text", "value": "Luyện thì hiện tại đơn và hiện tại tiếp diễn để nói về thói quen của bạn bè." }
                ]
              },
              {
                "title": "Bài 4: Communication",
                "videoUrl": "https://flutter.github.io/assets-for-api-docs/assets/videos/bee.mp4",
                "contents": [
                  { "type": "text", "value": "Thực hành hội thoại giới thiệu bạn bè và sở thích của họ." }
                ]
              },
              {
                "title": "Bài 5: Skills 1 - Reading & Speaking",
                "videoUrl": "https://flutter.github.io/assets-for-api-docs/assets/videos/bee.mp4",
                "contents": [
                  { "type": "text", "value": "Đọc hiểu đoạn văn về tình bạn và luyện nói về bạn thân của mình." }
                ]
              },
              {
                "title": "Bài 6: Skills 2 - Listening & Writing",
                "videoUrl": "https://flutter.github.io/assets-for-api-docs/assets/videos/bee.mp4",
                "contents": [
                  { "type": "text", "value": "Nghe đoạn hội thoại về bạn bè và viết đoạn văn giới thiệu bạn thân." }
                ]
              },
              {
                "title": "Bài 7: Looking Back & Project",
                "videoUrl": "https://flutter.github.io/assets-for-api-docs/assets/videos/bee.mp4",
                "contents": [
                  { "type": "text", "value": "Ôn tập từ vựng, ngữ pháp và thực hiện dự án về tình bạn." }
                ]
              }
            ]
          }
        ]
      }
    ]
  }
